<annotation>
  <folder>temp</folder>
  <filename>dataset119</filename>
  <path>C:\Users\USER\Downloads\labelimg\temp\dataset119.jpg</path>
  <source>
    <database>Unknown</database>
  </source>
  <size>
    <width>363</width>
    <height>363</height>
    <depth>3</depth>
  </size>
  <segmented>0</segmented>
  <object>
    <name>abnormal</name>
    <pose>Unspecified</pose>
    <truncated>0</truncated>
    <difficult>0</difficult>
    <bndbox>
      <xmin>181</xmin>
      <ymin>31</ymin>
      <xmax>253</xmax>
      <ymax>102</ymax>
    </bndbox>
  </object>
  <object>
    <name>cancer</name>
    <pose>Unspecified</pose>
    <truncated>0</truncated>
    <difficult>0</difficult>
    <bndbox>
      <xmin>20</xmin>
      <ymin>28</ymin>
      <xmax>100</xmax>
      <ymax>105</ymax>
    </bndbox>
  </object>
  <object>
    <name>normal</name>
    <pose>Unspecified</pose>
    <truncated>0</truncated>
    <difficult>0</difficult>
    <bndbox>
      <xmin>34</xmin>
      <ymin>209</ymin>
      <xmax>85</xmax>
      <ymax>264</ymax>
    </bndbox>
  </object>
  <object>
    <name>normal</name>
    <pose>Unspecified</pose>
    <truncated>0</truncated>
    <difficult>0</difficult>
    <bndbox>
      <xmin>251</xmin>
      <ymin>301</ymin>
      <xmax>308</xmax>
      <ymax>362</ymax>
    </bndbox>
  </object>
</annotation>
