<annotation>
  <folder>train</folder>
  <filename>dataset031</filename>
  <path>C:\Users\USER\Downloads\labelimg\train\dataset031.jpg</path>
  <source>
    <database>Unknown</database>
  </source>
  <size>
    <width>361</width>
    <height>361</height>
    <depth>3</depth>
  </size>
  <segmented>0</segmented>
  <object>
    <name>cancer</name>
    <pose>Unspecified</pose>
    <truncated>0</truncated>
    <difficult>0</difficult>
    <bndbox>
      <xmin>149</xmin>
      <ymin>197</ymin>
      <xmax>218</xmax>
      <ymax>268</ymax>
    </bndbox>
  </object>
  <object>
    <name>normal</name>
    <pose>Unspecified</pose>
    <truncated>0</truncated>
    <difficult>0</difficult>
    <bndbox>
      <xmin>317</xmin>
      <ymin>210</ymin>
      <xmax>361</xmax>
      <ymax>255</ymax>
    </bndbox>
  </object>
  <object>
    <name>normal</name>
    <pose>Unspecified</pose>
    <truncated>0</truncated>
    <difficult>0</difficult>
    <bndbox>
      <xmin>3</xmin>
      <ymin>215</ymin>
      <xmax>49</xmax>
      <ymax>257</ymax>
    </bndbox>
  </object>
  <object>
    <name>abnormal</name>
    <pose>Unspecified</pose>
    <truncated>0</truncated>
    <difficult>0</difficult>
    <bndbox>
      <xmin>138</xmin>
      <ymin>31</ymin>
      <xmax>235</xmax>
      <ymax>115</ymax>
    </bndbox>
  </object>
</annotation>
